{"pageProps":{"article":{"title":"Sports Briefs: Men’s Volleyball, Men’s Basketball","category":"Sports","subcategory":"Basketball","publish_date":"2011-02-28T08:00:00.000Z","full_thumbnail":"Not available","mobile_thumbnail":"Not available","description":"The #3 Gaucho men’s volleyball team took out #15 Pacific on Friday by a score of 3-1, before losing in five games to defending national champion Stanford the next day.","content":"<div class=\"single-post-content\">\n            <p>Stanford Stages Comeback on Home Floor to Win 3-2</p>\n<p>[media-credit name=”Jon Kopecky” align=”alignleft” width=”191″]<a href=\"https://i2.wp.com/www.dailynexus.com/wp-content/uploads/2011/02/JKopecky_MVball_17FEB2011_-43.jpg\" data-slb-active=\"1\" data-slb-asset=\"1575935620\" data-slb-group=\"34089\"><img data-attachment-id=\"34091\" data-permalink=\"https://dailynexus.com/2011-02-28/sports-briefs-mens-volleyball-mens-basketball/jkopecky_mvball_17feb2011_-43/\" data-orig-file=\"https://i2.wp.com/dailynexus.com/wp-content/uploads/2011/02/JKopecky_MVball_17FEB2011_-43.jpg?fit=613%2C800&amp;ssl=1\" data-orig-size=\"613,800\" data-comments-opened=\"1\" data-image-meta='{\"aperture\":\"3.2\",\"credit\":\"\",\"camera\":\"Canon EOS 40D\",\"caption\":\"\",\"created_timestamp\":\"1297977710\",\"copyright\":\"\",\"focal_length\":\"50\",\"iso\":\"1000\",\"shutter_speed\":\"0.003125\",\"title\":\"\",\"orientation\":\"1\"}' data-image-title=\"JKopecky_MVball_17FEB2011_ (43)\" data-image-description=\"\" data-medium-file=\"https://i2.wp.com/dailynexus.com/wp-content/uploads/2011/02/JKopecky_MVball_17FEB2011_-43.jpg?fit=192%2C250&amp;ssl=1\" data-large-file=\"https://i2.wp.com/dailynexus.com/wp-content/uploads/2011/02/JKopecky_MVball_17FEB2011_-43.jpg?fit=613%2C800&amp;ssl=1\" src=\"https://i0.wp.com/www.dailynexus.com/wp-content/uploads/2011/02/JKopecky_MVball_17FEB2011_-43-191x250.jpg?resize=191%2C250\" alt=\"\" title=\"JKopecky_MVball_17FEB2011_ (43)\" width=\"191\" height=\"250\" class=\"size-medium wp-image-34091\" data-recalc-dims=\"1\"></a>[/media-credit]The #3 Gaucho men’s volleyball team took out #15 Pacific on Friday by a score of 3-1, before losing in five games to defending national champion Stanford the next day.</p>\n<p>UCSB (10-7 overall, 8-6 MPSF) gave up its lead only twice throughout the first two games against the Cardinal, but after a 23-23 tie in the third, Stanford went on a tear, winning that frame along with the next two.</p><!--Ad Injection:random--><script type=\"text/javascript\"> \r\n\r\nfunction myAdDoneFunction(spotx_ad_found) { if(spotx_ad_found) {} else {}}; \r\n\r\n\r\n\r\nfunction mobileAndTabletcheck() { \r\n\r\nvar check = false; \r\n\r\n (function(a){if(/(android|bb\\d+|meego).+mobile|avantgo|bada\\/|blackberry|blazer|compal|elaine|fennec|hiptop|iemobile|ip(hone|od)|iris|kindle|lge |maemo|midp|mmp|mobile.+firefox|netfront|opera m(ob|in)i|palm( os)?|phone|p(ixi|re)\\/|plucker|pocket|psp|series(4|6)0|symbian|treo|up\\.(browser|link)|vodafone|wap|windows ce|xda|xiino|android|ipad|playbook|silk/i.test(a)||/1207|6310|6590|3gso|4thp|50[1-6]i|770s|802s|a wa|abac|ac(er|oo|s\\-)|ai(ko|rn)|al(av|ca|co)|amoi|an(ex|ny|yw)|aptu|ar(ch|go)|as(te|us)|attw|au(di|\\-m|r |s )|avan|be(ck|ll|nq)|bi(lb|rd)|bl(ac|az)|br(e|v)w|bumb|bw\\-(n|u)|c55\\/|capi|ccwa|cdm\\-|cell|chtm|cldc|cmd\\-|co(mp|nd)|craw|da(it|ll|ng)|dbte|dc\\-s|devi|dica|dmob|do(c|p)o|ds(12|\\-d)|el(49|ai)|em(l2|ul)|er(ic|k0)|esl8|ez([4-7]0|os|wa|ze)|fetc|fly(\\-|_)|g1 u|g560|gene|gf\\-5|g\\-mo|go(\\.w|od)|gr(ad|un)|haie|hcit|hd\\-(m|p|t)|hei\\-|hi(pt|ta)|hp( i|ip)|hs\\-c|ht(c(\\-| |_|a|g|p|s|t)|tp)|hu(aw|tc)|i\\-(20|go|ma)|i230|iac( |\\-|\\/)|ibro|idea|ig01|ikom|im1k|inno|ipaq|iris|ja(t|v)a|jbro|jemu|jigs|kddi|keji|kgt( |\\/)|klon|kpt |kwc\\-|kyo(c|k)|le(no|xi)|lg( g|\\/(k|l|u)|50|54|\\-[a-w])|libw|lynx|m1\\-w|m3ga|m50\\/|ma(te|ui|xo)|mc(01|21|ca)|m\\-cr|me(rc|ri)|mi(o8|oa|ts)|mmef|mo(01|02|bi|de|do|t(\\-| |o|v)|zz)|mt(50|p1|v )|mwbp|mywa|n10[0-2]|n20[2-3]|n30(0|2)|n50(0|2|5)|n7(0(0|1)|10)|ne((c|m)\\-|on|tf|wf|wg|wt)|nok(6|i)|nzph|o2im|op(ti|wv)|oran|owg1|p800|pan(a|d|t)|pdxg|pg(13|\\-([1-8]|c))|phil|pire|pl(ay|uc)|pn\\-2|po(ck|rt|se)|prox|psio|pt\\-g|qa\\-a|qc(07|12|21|32|60|\\-[2-7]|i\\-)|qtek|r380|r600|raks|rim9|ro(ve|zo)|s55\\/|sa(ge|ma|mm|ms|ny|va)|sc(01|h\\-|oo|p\\-)|sdk\\/|se(c(\\-|0|1)|47|mc|nd|ri)|sgh\\-|shar|sie(\\-|m)|sk\\-0|sl(45|id)|sm(al|ar|b3|it|t5)|so(ft|ny)|sp(01|h\\-|v\\-|v )|sy(01|mb)|t2(18|50)|t6(00|10|18)|ta(gt|lk)|tcl\\-|tdg\\-|tel(i|m)|tim\\-|t\\-mo|to(pl|sh)|ts(70|m\\-|m3|m5)|tx\\-9|up(\\.b|g1|si)|utst|v400|v750|veri|vi(rg|te)|vk(40|5[0-3]|\\-v)|vm40|voda|vulc|vx(52|53|60|61|70|80|81|83|85|98)|w3c(\\-| )|webc|whit|wi(g |nc|nw)|wmlb|wonu|x700|yas\\-|your|zeto|zte\\-/i.test(a.substr(0,4)))check = true})(navigator.userAgent||navigator.vendor||window.opera); \r\n\r\nreturn check; \r\n\r\n} \r\n\r\nvar bMobile = mobileAndTabletcheck(), \r\n\r\naScriptAttributes = [\r\n\r\n'type=\"text/javascript\" src=\"http://search.spotxchange.com/js/spotx.js\" data-spotx_ad_done_function=\"myAdDoneFunction\" data-spotx_ad_unit=\"incontent\" data-spotx_autoplay=\"1\" data-spotx_ad_volume=\"0\" data-spotx_loop=\"0\" data-spotx_collapse=\"1\" data-spotx_unmute_on_mouse=\"1\"'\r\n\r\n];\r\n\r\nif (bMobile) \r\n\r\n{ \r\n\r\naScriptAttributes.push('data-spotx_content_width=\"304\"'); \r\n\r\naScriptAttributes.push('data-spotx_content_height=\"171\"');\r\n\r\naScriptAttributes.push('data-spotx_channel_id=\"128967\"');\r\n\r\n} \r\n\r\nelse \r\n\r\n{ \r\n\r\naScriptAttributes.push('data-spotx_content_width=\"608\"'); \r\n\r\naScriptAttributes.push('data-spotx_content_height=\"342\"'); \r\n\r\naScriptAttributes.push('data-spotx_unmute_on_mouse=\"1\"');\r\n\r\naScriptAttributes.push('data-spotx_channel_id=\"108869\"');\r\n\r\n} \r\n\r\ndocument.write('<scr' + 'ipt ' + aScriptAttributes.join(\" \") + '></scr' + 'ipt>'); \r\n</script> \n<p>Stanford junior Brad Lawson tallied 25 kills on the night, which is the most UCSB has allowed so far this season. The Cardinal also hit over .500 as a team in the third and fifth games.</p>\n<p>Senior outside hitter Jeff Menzel had 16 kills on Saturday, which pushes his double-digit kill streak to 10 straight matches. Senior outside hitter Cullen Irons added 15 of his own for UCSB.</p>\n<p>The team will have to put the loss behind them this week, with a pair of home matches looming. The Gauchos host Long Beach State on Wednesday before taking on Cal State Northridge on Friday. Both matches will be held in Robertson Gymnasium at 7 p.m.</p>\n<p>49ers Use 20-0 Run to Hand UCSB Third Straight Loss</p>\n<p>The Gauchos were down by only three at the half, but Long Beach State outscored UCSB by 15 points in the second to win 71-53.</p>\n<p>UCSB junior guard Orlando Johnson scored 18 points in the loss, which was the Gauchos’ third consecutive. Long Beach guard Casper Ware scored 17 points in the first half and led all scorers with 26.  Forward T.J. Robinson posted a double-double with 19 points and 19 rebounds. As a team, UCSB grabbed 22 boards.</p>\n<p>With only two conference losses, Long Beach has long since secured the top seed in the Big West heading into the conference tournament. At 10-5, UCSB rival Cal Poly is in second place. While the Gauchos have clinched a Big West Tournament berth, the loss drops them to 7-8 and out of contention for third and fourth place, which will be held by Pacific and Cal State Northridge. Both teams are currently 8-6 in the Big West.</p>\n<p>As the conference picture stands, fifth-place UCSB will face Cal Poly in the first round of the tournament. The two teams will face off in the Gauchos’ final game of the season on March 5 at 7 p.m. at the Thunderdome.</p><div class=\"h5ab-print-button-container\"><div class=\"h5ab-print-button h5ab-print-button-left\" style=\"cursor: pointer; color: #555\"><i class=\"fa fa-print fa-lg\"></i>\n\t\t\t\t\t\t\t<span>Print</span></div></div>\n<div class=\"sharedaddy sd-sharing-enabled\"><div class=\"robots-nocontent sd-block sd-social sd-social-icon sd-sharing\"><h3 class=\"sd-title\">Share this:</h3><div class=\"sd-content\"><ul><li class=\"share-facebook\"><a rel=\"nofollow noopener noreferrer\" data-shared=\"sharing-facebook-34089\" class=\"share-facebook sd-button share-icon no-text\" href=\"https://dailynexus.com/2011-02-28/sports-briefs-mens-volleyball-mens-basketball/?share=facebook\" target=\"_blank\" title=\"Click to share on Facebook\"><span></span><span class=\"sharing-screen-reader-text\">Click to share on Facebook (Opens in new window)</span></a></li><li class=\"share-twitter\"><a rel=\"nofollow noopener noreferrer\" data-shared=\"sharing-twitter-34089\" class=\"share-twitter sd-button share-icon no-text\" href=\"https://dailynexus.com/2011-02-28/sports-briefs-mens-volleyball-mens-basketball/?share=twitter\" target=\"_blank\" title=\"Click to share on Twitter\"><span></span><span class=\"sharing-screen-reader-text\">Click to share on Twitter (Opens in new window)</span></a></li><li class=\"share-tumblr\"><a rel=\"nofollow noopener noreferrer\" data-shared=\"\" class=\"share-tumblr sd-button share-icon no-text\" href=\"https://dailynexus.com/2011-02-28/sports-briefs-mens-volleyball-mens-basketball/?share=tumblr\" target=\"_blank\" title=\"Click to share on Tumblr\"><span></span><span class=\"sharing-screen-reader-text\">Click to share on Tumblr (Opens in new window)</span></a></li><li class=\"share-reddit\"><a rel=\"nofollow noopener noreferrer\" data-shared=\"\" class=\"share-reddit sd-button share-icon no-text\" href=\"https://dailynexus.com/2011-02-28/sports-briefs-mens-volleyball-mens-basketball/?share=reddit\" target=\"_blank\" title=\"Click to share on Reddit\"><span></span><span class=\"sharing-screen-reader-text\">Click to share on Reddit (Opens in new window)</span></a></li><li class=\"share-end\"></ul></div></div></div>\n<div id=\"jp-relatedposts\" class=\"jp-relatedposts\">\n\t<h3 class=\"jp-relatedposts-headline\"><em>Related</em></h3>\n</div>          </div>","src_url":"https://dailynexus.com/2011-02-28/sports-briefs-mens-volleyball-mens-basketball/","id":855,"author":{"id":192,"name":"David Russo"},"related":[854,853,852],"comments":[],"followers":[]},"author":{"id":192,"name":"David Russo","biography":"Not available","articles":[237,239,240,241,242,243,244,245,252,256,257,259,260,261,262,263,264,265,266,267,269,272,274,275,276,277,279,490,491,855,1682,1769,4525,5196,5215,5244,5296,5408,5437,5438,5439,5440,5441,5442,5443,5444,5445,5446,5447,5456,5460,5462,5465,5467,5468,5470,5472,5473,5474,5475,5488],"portrait":"Not available"},"related":[{"title":"Team Ousts Titans in Big West Rematch","category":"Sports","subcategory":"Basketball","publish_date":"2011-02-17T08:00:00.000Z","full_thumbnail":"Not available","mobile_thumbnail":"Not available","description":"Junior forward James Nunnally grabbed a career-high 13 rebounds and senior point guard Justin Joyner added a collegiate-best 12 assists in the UCSB men’s basketball team’s 86-71 win over Cal State...","content":"<div class=\"single-post-content\">\n            <p>Junior forward James Nunnally grabbed a career-high 13 rebounds and senior point guard Justin Joyner added a collegiate-best 12 assists in the UCSB men’s basketball team’s 86-71 win over Cal State Fullerton last night in the Thunderdome.</p>\n<p><span>[media-credit id=20281 align=”aligncenter” width=”193″]<a href=\"http://www.dailynexus.com/2011-02-17/team-ousts-titans-big-west-rematch/wade_16feb11mbball_7/\" rel=\"attachment wp-att-33527\"><img src=\"https://i2.wp.com/www.dailynexus.com/wp-content/uploads/2011/02/Wade_16FEB11MBBall_7-193x250.jpg?resize=193%2C250\" alt=\"\" width=\"193\" height=\"250\" class=\"size-medium wp-image-33527\" data-recalc-dims=\"1\"></a>[/media-credit]</span> “I was just trying to get my Rondo on,” Joyner said.</p>\n<p>After losing to Fullerton in the last meeting between the two teams, UCSB (7-6 in league) has climbed to the fourth spot in Big West play. With the loss, the Titans drop to sixth place in the conference with a 5-8. CSUF senior guard Devon Peltier scored 17 of his team-high 19 points in the first half.</p><!--Ad Injection:random--><script type=\"text/javascript\"> \r\n\r\nfunction myAdDoneFunction(spotx_ad_found) { if(spotx_ad_found) {} else {}}; \r\n\r\n\r\n\r\nfunction mobileAndTabletcheck() { \r\n\r\nvar check = false; \r\n\r\n (function(a){if(/(android|bb\\d+|meego).+mobile|avantgo|bada\\/|blackberry|blazer|compal|elaine|fennec|hiptop|iemobile|ip(hone|od)|iris|kindle|lge |maemo|midp|mmp|mobile.+firefox|netfront|opera m(ob|in)i|palm( os)?|phone|p(ixi|re)\\/|plucker|pocket|psp|series(4|6)0|symbian|treo|up\\.(browser|link)|vodafone|wap|windows ce|xda|xiino|android|ipad|playbook|silk/i.test(a)||/1207|6310|6590|3gso|4thp|50[1-6]i|770s|802s|a wa|abac|ac(er|oo|s\\-)|ai(ko|rn)|al(av|ca|co)|amoi|an(ex|ny|yw)|aptu|ar(ch|go)|as(te|us)|attw|au(di|\\-m|r |s )|avan|be(ck|ll|nq)|bi(lb|rd)|bl(ac|az)|br(e|v)w|bumb|bw\\-(n|u)|c55\\/|capi|ccwa|cdm\\-|cell|chtm|cldc|cmd\\-|co(mp|nd)|craw|da(it|ll|ng)|dbte|dc\\-s|devi|dica|dmob|do(c|p)o|ds(12|\\-d)|el(49|ai)|em(l2|ul)|er(ic|k0)|esl8|ez([4-7]0|os|wa|ze)|fetc|fly(\\-|_)|g1 u|g560|gene|gf\\-5|g\\-mo|go(\\.w|od)|gr(ad|un)|haie|hcit|hd\\-(m|p|t)|hei\\-|hi(pt|ta)|hp( i|ip)|hs\\-c|ht(c(\\-| |_|a|g|p|s|t)|tp)|hu(aw|tc)|i\\-(20|go|ma)|i230|iac( |\\-|\\/)|ibro|idea|ig01|ikom|im1k|inno|ipaq|iris|ja(t|v)a|jbro|jemu|jigs|kddi|keji|kgt( |\\/)|klon|kpt |kwc\\-|kyo(c|k)|le(no|xi)|lg( g|\\/(k|l|u)|50|54|\\-[a-w])|libw|lynx|m1\\-w|m3ga|m50\\/|ma(te|ui|xo)|mc(01|21|ca)|m\\-cr|me(rc|ri)|mi(o8|oa|ts)|mmef|mo(01|02|bi|de|do|t(\\-| |o|v)|zz)|mt(50|p1|v )|mwbp|mywa|n10[0-2]|n20[2-3]|n30(0|2)|n50(0|2|5)|n7(0(0|1)|10)|ne((c|m)\\-|on|tf|wf|wg|wt)|nok(6|i)|nzph|o2im|op(ti|wv)|oran|owg1|p800|pan(a|d|t)|pdxg|pg(13|\\-([1-8]|c))|phil|pire|pl(ay|uc)|pn\\-2|po(ck|rt|se)|prox|psio|pt\\-g|qa\\-a|qc(07|12|21|32|60|\\-[2-7]|i\\-)|qtek|r380|r600|raks|rim9|ro(ve|zo)|s55\\/|sa(ge|ma|mm|ms|ny|va)|sc(01|h\\-|oo|p\\-)|sdk\\/|se(c(\\-|0|1)|47|mc|nd|ri)|sgh\\-|shar|sie(\\-|m)|sk\\-0|sl(45|id)|sm(al|ar|b3|it|t5)|so(ft|ny)|sp(01|h\\-|v\\-|v )|sy(01|mb)|t2(18|50)|t6(00|10|18)|ta(gt|lk)|tcl\\-|tdg\\-|tel(i|m)|tim\\-|t\\-mo|to(pl|sh)|ts(70|m\\-|m3|m5)|tx\\-9|up(\\.b|g1|si)|utst|v400|v750|veri|vi(rg|te)|vk(40|5[0-3]|\\-v)|vm40|voda|vulc|vx(52|53|60|61|70|80|81|83|85|98)|w3c(\\-| )|webc|whit|wi(g |nc|nw)|wmlb|wonu|x700|yas\\-|your|zeto|zte\\-/i.test(a.substr(0,4)))check = true})(navigator.userAgent||navigator.vendor||window.opera); \r\n\r\nreturn check; \r\n\r\n} \r\n\r\nvar bMobile = mobileAndTabletcheck(), \r\n\r\naScriptAttributes = [\r\n\r\n'type=\"text/javascript\" src=\"http://search.spotxchange.com/js/spotx.js\" data-spotx_ad_done_function=\"myAdDoneFunction\" data-spotx_ad_unit=\"incontent\" data-spotx_autoplay=\"1\" data-spotx_ad_volume=\"0\" data-spotx_loop=\"0\" data-spotx_collapse=\"1\" data-spotx_unmute_on_mouse=\"1\"'\r\n\r\n];\r\n\r\nif (bMobile) \r\n\r\n{ \r\n\r\naScriptAttributes.push('data-spotx_content_width=\"304\"'); \r\n\r\naScriptAttributes.push('data-spotx_content_height=\"171\"');\r\n\r\naScriptAttributes.push('data-spotx_channel_id=\"128967\"');\r\n\r\n} \r\n\r\nelse \r\n\r\n{ \r\n\r\naScriptAttributes.push('data-spotx_content_width=\"608\"'); \r\n\r\naScriptAttributes.push('data-spotx_content_height=\"342\"'); \r\n\r\naScriptAttributes.push('data-spotx_unmute_on_mouse=\"1\"');\r\n\r\naScriptAttributes.push('data-spotx_channel_id=\"108869\"');\r\n\r\n} \r\n\r\ndocument.write('<scr' + 'ipt ' + aScriptAttributes.join(\" \") + '></scr' + 'ipt>'); \r\n</script> \n<p>“The first half we gambled more [on defense],” UCSB Head Coach Bob Williams said. “[Peltier] got hot and knocked down some shots in that first half.”</p>\n<p>UCSB hit the majority of its shots as well during the first twenty minutes of play. Led by Nunnally’s 27 points and junior Orlando Johnson’s 20, the Gauchos shot 60 percent from the field. UCSB’s bench scored 15 of the team’s 45 points in the first half.</p>\n<p>“Balanced scoring was the key for us,” Joyner said. “When we have balanced scoring we’re harder to guard.”</p>\n<p>Junior Greg Somogyi again proved to be an important asset for the Gauchos off the bench. “The Storke Tower” scored within 15 seconds of stepping on the floor for UCSB in the first period, and finished the half with one block and seven points, making three of his four field goal attempts.</p>\n<p>“[Somogyi] is a big part of this team,” Joyner said. “When he plays at that level that makes us a lot better of a team offensively and defensively.”</p>\n<p>UCSB maintained the lead throughout the second half thanks in part to aggressive play by Nunnally, who made eight of 10 free throws on the night.</p>\n<p>“It was a phenomenal performance,” Williams said. “He was a really dynamic player. I thought he played really well.”</p>\n<p>After leading by as many as 20 points in the first half, the Gaucho lead hovered around 10 throughout the second period. An inside basket by Fullerton junior Andre Hardy cut the lead to 71-63 with just 4:20 remaining in the game.</p>\n<p>UCSB junior Orlando Johnson made a deep three-point shot to move the lead back to double digits, but his basket was quickly answered by a Peltier jumper that brought the score to 74-65 with 2:43 to play.</p>\n<p>Nunnally’s NBA-range threepointer with 1:45 remaining in the game extended the Gaucho lead to 79-65 and secured the victory for UCSB.</p>\n<p>“We want to be the team that everybody’s scared of,” Nunnally said. “If we keep the pressure and the intensity up we can do that.”</p>\n<p>UCSB faces non-conference Boise State in an ESPN Bracketbuster game at the Thunderdome in its next game on Saturday Feb. 19 at 7 p.m.</p><div class=\"h5ab-print-button-container\"><div class=\"h5ab-print-button h5ab-print-button-left\" style=\"cursor: pointer; color: #555\"><i class=\"fa fa-print fa-lg\"></i>\n\t\t\t\t\t\t\t<span>Print</span></div></div>\n<div class=\"sharedaddy sd-sharing-enabled\"><div class=\"robots-nocontent sd-block sd-social sd-social-icon sd-sharing\"><h3 class=\"sd-title\">Share this:</h3><div class=\"sd-content\"><ul><li class=\"share-facebook\"><a rel=\"nofollow noopener noreferrer\" data-shared=\"sharing-facebook-33525\" class=\"share-facebook sd-button share-icon no-text\" href=\"https://dailynexus.com/2011-02-17/team-ousts-titans-big-west-rematch/?share=facebook\" target=\"_blank\" title=\"Click to share on Facebook\"><span></span><span class=\"sharing-screen-reader-text\">Click to share on Facebook (Opens in new window)</span></a></li><li class=\"share-twitter\"><a rel=\"nofollow noopener noreferrer\" data-shared=\"sharing-twitter-33525\" class=\"share-twitter sd-button share-icon no-text\" href=\"https://dailynexus.com/2011-02-17/team-ousts-titans-big-west-rematch/?share=twitter\" target=\"_blank\" title=\"Click to share on Twitter\"><span></span><span class=\"sharing-screen-reader-text\">Click to share on Twitter (Opens in new window)</span></a></li><li class=\"share-tumblr\"><a rel=\"nofollow noopener noreferrer\" data-shared=\"\" class=\"share-tumblr sd-button share-icon no-text\" href=\"https://dailynexus.com/2011-02-17/team-ousts-titans-big-west-rematch/?share=tumblr\" target=\"_blank\" title=\"Click to share on Tumblr\"><span></span><span class=\"sharing-screen-reader-text\">Click to share on Tumblr (Opens in new window)</span></a></li><li class=\"share-reddit\"><a rel=\"nofollow noopener noreferrer\" data-shared=\"\" class=\"share-reddit sd-button share-icon no-text\" href=\"https://dailynexus.com/2011-02-17/team-ousts-titans-big-west-rematch/?share=reddit\" target=\"_blank\" title=\"Click to share on Reddit\"><span></span><span class=\"sharing-screen-reader-text\">Click to share on Reddit (Opens in new window)</span></a></li><li class=\"share-end\"></ul></div></div></div>\n<div id=\"jp-relatedposts\" class=\"jp-relatedposts\">\n\t<h3 class=\"jp-relatedposts-headline\"><em>Related</em></h3>\n</div>          </div>","src_url":"https://dailynexus.com/2011-02-17/team-ousts-titans-big-west-rematch/","id":852,"author":{"id":78,"name":"Brent Pella"},"related":[851,850,849],"comments":[],"followers":[]},{"title":"Valentine Leads UCSB to Victory Over Seattle","category":"Sports","subcategory":"Basketball","publish_date":"2011-02-21T08:00:00.000Z","full_thumbnail":"Not available","mobile_thumbnail":"Not available","description":"The Gauchos withstood a tenacious rally from the Redhawks, defeating visiting Seattle University 67-57 in a nonconference match up and improving their record to 16-10 on the season. The game also mark...","content":"<div class=\"single-post-content\">\n            <p>The Gauchos withstood a tenacious rally from the Redhawks, defeating visiting Seattle University 67-57 in a nonconference match up and improving their record to 16-10 on the season. The game also marked this year’s Pink Zone game, which raises breast cancer awareness.</p>\n<p><span>[media-credit id=20125 align=”alignright” width=”161″]<a href=\"http://www.dailynexus.com/2011-02-21/valentine-leads-ucsb-victory-seattle/jkopecky_14feb2011wbball_-14/\" rel=\"attachment wp-att-33682\"><img data-attachment-id=\"33682\" data-permalink=\"https://dailynexus.com/2011-02-21/valentine-leads-ucsb-victory-seattle/jkopecky_14feb2011wbball_-14/\" data-orig-file=\"https://i2.wp.com/dailynexus.com/wp-content/uploads/2011/02/JKopecky_14Feb2011WBball_-14.jpg?fit=517%2C800&amp;ssl=1\" data-orig-size=\"517,800\" data-comments-opened=\"1\" data-image-meta='{\"aperture\":\"9\",\"credit\":\"\",\"camera\":\"Canon EOS 40D\",\"caption\":\"\",\"created_timestamp\":\"1297528270\",\"copyright\":\"\",\"focal_length\":\"20\",\"iso\":\"400\",\"shutter_speed\":\"0.004\",\"title\":\"\",\"orientation\":\"1\"}' data-image-title=\"JKopecky_14Feb2011WBball_ (14)\" data-image-description=\"\" data-medium-file=\"https://i2.wp.com/dailynexus.com/wp-content/uploads/2011/02/JKopecky_14Feb2011WBball_-14.jpg?fit=162%2C250&amp;ssl=1\" data-large-file=\"https://i2.wp.com/dailynexus.com/wp-content/uploads/2011/02/JKopecky_14Feb2011WBball_-14.jpg?fit=517%2C800&amp;ssl=1\" src=\"https://i0.wp.com/www.dailynexus.com/wp-content/uploads/2011/02/JKopecky_14Feb2011WBball_-14-161x250.jpg?resize=161%2C250\" alt=\"\" width=\"161\" height=\"250\" class=\"size-medium wp-image-33682\" data-recalc-dims=\"1\"></a>[/media-credit]</span>Junior guard Emilie Johnson led the Gauchos with 19 points and senior forward Mekia Valentine had a 13-point, 17-rebound double-double to go with her seven blocked shots. Valentine also earned the Big West’s Player of the Week Award this week.</p>\n<p>“We’re really excited to get a win on Pink Zone day,” Head Coach Lindsay Gottlieb said. “We came out and [Emilie] was absolutely on fire in the first half. Mekia dominated the game from the rebounding and defensive standpoint.”</p><!--Ad Injection:random--><script type=\"text/javascript\"> \r\n\r\nfunction myAdDoneFunction(spotx_ad_found) { if(spotx_ad_found) {} else {}}; \r\n\r\n\r\n\r\nfunction mobileAndTabletcheck() { \r\n\r\nvar check = false; \r\n\r\n (function(a){if(/(android|bb\\d+|meego).+mobile|avantgo|bada\\/|blackberry|blazer|compal|elaine|fennec|hiptop|iemobile|ip(hone|od)|iris|kindle|lge |maemo|midp|mmp|mobile.+firefox|netfront|opera m(ob|in)i|palm( os)?|phone|p(ixi|re)\\/|plucker|pocket|psp|series(4|6)0|symbian|treo|up\\.(browser|link)|vodafone|wap|windows ce|xda|xiino|android|ipad|playbook|silk/i.test(a)||/1207|6310|6590|3gso|4thp|50[1-6]i|770s|802s|a wa|abac|ac(er|oo|s\\-)|ai(ko|rn)|al(av|ca|co)|amoi|an(ex|ny|yw)|aptu|ar(ch|go)|as(te|us)|attw|au(di|\\-m|r |s )|avan|be(ck|ll|nq)|bi(lb|rd)|bl(ac|az)|br(e|v)w|bumb|bw\\-(n|u)|c55\\/|capi|ccwa|cdm\\-|cell|chtm|cldc|cmd\\-|co(mp|nd)|craw|da(it|ll|ng)|dbte|dc\\-s|devi|dica|dmob|do(c|p)o|ds(12|\\-d)|el(49|ai)|em(l2|ul)|er(ic|k0)|esl8|ez([4-7]0|os|wa|ze)|fetc|fly(\\-|_)|g1 u|g560|gene|gf\\-5|g\\-mo|go(\\.w|od)|gr(ad|un)|haie|hcit|hd\\-(m|p|t)|hei\\-|hi(pt|ta)|hp( i|ip)|hs\\-c|ht(c(\\-| |_|a|g|p|s|t)|tp)|hu(aw|tc)|i\\-(20|go|ma)|i230|iac( |\\-|\\/)|ibro|idea|ig01|ikom|im1k|inno|ipaq|iris|ja(t|v)a|jbro|jemu|jigs|kddi|keji|kgt( |\\/)|klon|kpt |kwc\\-|kyo(c|k)|le(no|xi)|lg( g|\\/(k|l|u)|50|54|\\-[a-w])|libw|lynx|m1\\-w|m3ga|m50\\/|ma(te|ui|xo)|mc(01|21|ca)|m\\-cr|me(rc|ri)|mi(o8|oa|ts)|mmef|mo(01|02|bi|de|do|t(\\-| |o|v)|zz)|mt(50|p1|v )|mwbp|mywa|n10[0-2]|n20[2-3]|n30(0|2)|n50(0|2|5)|n7(0(0|1)|10)|ne((c|m)\\-|on|tf|wf|wg|wt)|nok(6|i)|nzph|o2im|op(ti|wv)|oran|owg1|p800|pan(a|d|t)|pdxg|pg(13|\\-([1-8]|c))|phil|pire|pl(ay|uc)|pn\\-2|po(ck|rt|se)|prox|psio|pt\\-g|qa\\-a|qc(07|12|21|32|60|\\-[2-7]|i\\-)|qtek|r380|r600|raks|rim9|ro(ve|zo)|s55\\/|sa(ge|ma|mm|ms|ny|va)|sc(01|h\\-|oo|p\\-)|sdk\\/|se(c(\\-|0|1)|47|mc|nd|ri)|sgh\\-|shar|sie(\\-|m)|sk\\-0|sl(45|id)|sm(al|ar|b3|it|t5)|so(ft|ny)|sp(01|h\\-|v\\-|v )|sy(01|mb)|t2(18|50)|t6(00|10|18)|ta(gt|lk)|tcl\\-|tdg\\-|tel(i|m)|tim\\-|t\\-mo|to(pl|sh)|ts(70|m\\-|m3|m5)|tx\\-9|up(\\.b|g1|si)|utst|v400|v750|veri|vi(rg|te)|vk(40|5[0-3]|\\-v)|vm40|voda|vulc|vx(52|53|60|61|70|80|81|83|85|98)|w3c(\\-| )|webc|whit|wi(g |nc|nw)|wmlb|wonu|x700|yas\\-|your|zeto|zte\\-/i.test(a.substr(0,4)))check = true})(navigator.userAgent||navigator.vendor||window.opera); \r\n\r\nreturn check; \r\n\r\n} \r\n\r\nvar bMobile = mobileAndTabletcheck(), \r\n\r\naScriptAttributes = [\r\n\r\n'type=\"text/javascript\" src=\"http://search.spotxchange.com/js/spotx.js\" data-spotx_ad_done_function=\"myAdDoneFunction\" data-spotx_ad_unit=\"incontent\" data-spotx_autoplay=\"1\" data-spotx_ad_volume=\"0\" data-spotx_loop=\"0\" data-spotx_collapse=\"1\" data-spotx_unmute_on_mouse=\"1\"'\r\n\r\n];\r\n\r\nif (bMobile) \r\n\r\n{ \r\n\r\naScriptAttributes.push('data-spotx_content_width=\"304\"'); \r\n\r\naScriptAttributes.push('data-spotx_content_height=\"171\"');\r\n\r\naScriptAttributes.push('data-spotx_channel_id=\"128967\"');\r\n\r\n} \r\n\r\nelse \r\n\r\n{ \r\n\r\naScriptAttributes.push('data-spotx_content_width=\"608\"'); \r\n\r\naScriptAttributes.push('data-spotx_content_height=\"342\"'); \r\n\r\naScriptAttributes.push('data-spotx_unmute_on_mouse=\"1\"');\r\n\r\naScriptAttributes.push('data-spotx_channel_id=\"108869\"');\r\n\r\n} \r\n\r\ndocument.write('<scr' + 'ipt ' + aScriptAttributes.join(\" \") + '></scr' + 'ipt>'); \r\n</script> \n<p>After taking a 35-23 lead to end the first half, Seattle rallied in the second to cut the lead to three but the Gauchos made some clutch baskets to close out the game.</p>\n<p>“We had to adjust, and Sweets [Underwood] and Nicole [Nesbit] hit some big shots in the second half,” Gottlieb said. “We had some defensive breakdowns but I love how we responded when they made it close.”</p>\n<p>UCSB was also playing without starting guard Kelsey Adrian, the team’s third-leading point scorer and leader in minutes played.</p>\n<p>Nesbit scored 12 points for the Gauchos, while freshman guard Melissa Zornig added five points, four rebounds and three assists. Underwood had a big day for UCSB with 11 points and seven rebounds.</p>\n<p>“We don’t expect to miss a beat,” Gottlieb said. “That doesn’t take anything away from Kelsey, but we expected the level [of play] to be the same. It builds confidence and hopefully those kids coming off the bench are even more ready to come in and do what we need when Kelsey is back.”</p>\n<p>Seattle’s Elle Kerfoot led all scorers with 20 points. The Redhawks double-teamed Valentine constantly throughout the first half, limiting her to four points in the period.</p>\n<p>“I’ve gotten used to facing double teams, and I was more focused on my defense than on my offense,” Valentine said. “I was confident that my teammates were going to knock down shots and eventually that opened things up for me in the second half.”</p>\n<p>After a tumultuous weekend in which first-place Cal Poly lost to both Northridge and Riverside, the Gauchos are now in second place and only one game behind the Mustangs, putting them within striking distance of a regular season conference title.</p>\n<p>“We want to win a championship, that has been a motivating factor all along,” Gottlieb said. “But we can’t even discuss the chance to have a championship unless we take care of our own business.”</p>\n<p>Both teams have a pair of conference match-ups left on their schedule. Should both win out, the last conference game of the season between the two frontrunners in San Luis Obispo would decide the regular season title.</p>\n<p>“Our players really have a healthy understanding that we don’t get to talk about any championships if we don’t win our games,” Gottlieb said. “If the opportunity does present itself, where we get a game up at Cal Poly that really means something. Then that is pretty exciting.”</p>\n<p>In its next game, UCSB faces Long Beach at the Thunderdome on Feb. 24. Tip-off is scheduled for 7 p.m.</p><div class=\"h5ab-print-button-container\"><div class=\"h5ab-print-button h5ab-print-button-left\" style=\"cursor: pointer; color: #555\"><i class=\"fa fa-print fa-lg\"></i>\n\t\t\t\t\t\t\t<span>Print</span></div></div>\n<div class=\"sharedaddy sd-sharing-enabled\"><div class=\"robots-nocontent sd-block sd-social sd-social-icon sd-sharing\"><h3 class=\"sd-title\">Share this:</h3><div class=\"sd-content\"><ul><li class=\"share-facebook\"><a rel=\"nofollow noopener noreferrer\" data-shared=\"sharing-facebook-33680\" class=\"share-facebook sd-button share-icon no-text\" href=\"https://dailynexus.com/2011-02-21/valentine-leads-ucsb-victory-seattle/?share=facebook\" target=\"_blank\" title=\"Click to share on Facebook\"><span></span><span class=\"sharing-screen-reader-text\">Click to share on Facebook (Opens in new window)</span></a></li><li class=\"share-twitter\"><a rel=\"nofollow noopener noreferrer\" data-shared=\"sharing-twitter-33680\" class=\"share-twitter sd-button share-icon no-text\" href=\"https://dailynexus.com/2011-02-21/valentine-leads-ucsb-victory-seattle/?share=twitter\" target=\"_blank\" title=\"Click to share on Twitter\"><span></span><span class=\"sharing-screen-reader-text\">Click to share on Twitter (Opens in new window)</span></a></li><li class=\"share-tumblr\"><a rel=\"nofollow noopener noreferrer\" data-shared=\"\" class=\"share-tumblr sd-button share-icon no-text\" href=\"https://dailynexus.com/2011-02-21/valentine-leads-ucsb-victory-seattle/?share=tumblr\" target=\"_blank\" title=\"Click to share on Tumblr\"><span></span><span class=\"sharing-screen-reader-text\">Click to share on Tumblr (Opens in new window)</span></a></li><li class=\"share-reddit\"><a rel=\"nofollow noopener noreferrer\" data-shared=\"\" class=\"share-reddit sd-button share-icon no-text\" href=\"https://dailynexus.com/2011-02-21/valentine-leads-ucsb-victory-seattle/?share=reddit\" target=\"_blank\" title=\"Click to share on Reddit\"><span></span><span class=\"sharing-screen-reader-text\">Click to share on Reddit (Opens in new window)</span></a></li><li class=\"share-end\"></ul></div></div></div>\n<div id=\"jp-relatedposts\" class=\"jp-relatedposts\">\n\t<h3 class=\"jp-relatedposts-headline\"><em>Related</em></h3>\n</div>          </div>","src_url":"https://dailynexus.com/2011-02-21/valentine-leads-ucsb-victory-seattle/","id":853,"author":{"id":72,"name":"Paul-Michael Ochoa"},"related":[852,851,850],"comments":[],"followers":[]},{"title":"Gauchos Escape Fullerton With Victory","category":"Sports","subcategory":"Basketball","publish_date":"2011-02-18T08:00:00.000Z","full_thumbnail":"Not available","mobile_thumbnail":"Not available","description":"Against a Fullerton team determined to get revenge for a 37-point loss earlier this season, UCSB women’s basketball narrowly escaped Titan Gym on Thursday night with its 73-70 victory.","content":"<div class=\"single-post-content\">\n            <p>Against a Fullerton team determined to get revenge for a 37-point loss earlier this season, UCSB women’s basketball narrowly escaped Titan Gym on Thursday night with its 73-70 victory. In the game’s closing seconds, Fullerton missed a three-pointer that would have sent the game into overtime, securing the victory for the Gauchos.</p>\n<p>UCSB improves to 15-10 overall (9-4 Big West), while Fullerton falls to 8-18 (4-9 Big West) and into a tie for last place in the conference with the loss. Senior forward Mekia Valentine led UCSB to its 37th consecutive victory over Fullerton with 11 points, 16 rebounds and five blocked shots.</p>\n<p>“[Mekia] was tremendous,” Head Coach Lindsay Gottlieb said. “She asserted herself as one of the dominant rebounders in the league tonight. She controlled the game with her defense and rebounding throughout and shot the ball extremely well. Mekia really stepped up tonight.”</p><!--Ad Injection:random--><script type=\"text/javascript\"> \r\n\r\nfunction myAdDoneFunction(spotx_ad_found) { if(spotx_ad_found) {} else {}}; \r\n\r\n\r\n\r\nfunction mobileAndTabletcheck() { \r\n\r\nvar check = false; \r\n\r\n (function(a){if(/(android|bb\\d+|meego).+mobile|avantgo|bada\\/|blackberry|blazer|compal|elaine|fennec|hiptop|iemobile|ip(hone|od)|iris|kindle|lge |maemo|midp|mmp|mobile.+firefox|netfront|opera m(ob|in)i|palm( os)?|phone|p(ixi|re)\\/|plucker|pocket|psp|series(4|6)0|symbian|treo|up\\.(browser|link)|vodafone|wap|windows ce|xda|xiino|android|ipad|playbook|silk/i.test(a)||/1207|6310|6590|3gso|4thp|50[1-6]i|770s|802s|a wa|abac|ac(er|oo|s\\-)|ai(ko|rn)|al(av|ca|co)|amoi|an(ex|ny|yw)|aptu|ar(ch|go)|as(te|us)|attw|au(di|\\-m|r |s )|avan|be(ck|ll|nq)|bi(lb|rd)|bl(ac|az)|br(e|v)w|bumb|bw\\-(n|u)|c55\\/|capi|ccwa|cdm\\-|cell|chtm|cldc|cmd\\-|co(mp|nd)|craw|da(it|ll|ng)|dbte|dc\\-s|devi|dica|dmob|do(c|p)o|ds(12|\\-d)|el(49|ai)|em(l2|ul)|er(ic|k0)|esl8|ez([4-7]0|os|wa|ze)|fetc|fly(\\-|_)|g1 u|g560|gene|gf\\-5|g\\-mo|go(\\.w|od)|gr(ad|un)|haie|hcit|hd\\-(m|p|t)|hei\\-|hi(pt|ta)|hp( i|ip)|hs\\-c|ht(c(\\-| |_|a|g|p|s|t)|tp)|hu(aw|tc)|i\\-(20|go|ma)|i230|iac( |\\-|\\/)|ibro|idea|ig01|ikom|im1k|inno|ipaq|iris|ja(t|v)a|jbro|jemu|jigs|kddi|keji|kgt( |\\/)|klon|kpt |kwc\\-|kyo(c|k)|le(no|xi)|lg( g|\\/(k|l|u)|50|54|\\-[a-w])|libw|lynx|m1\\-w|m3ga|m50\\/|ma(te|ui|xo)|mc(01|21|ca)|m\\-cr|me(rc|ri)|mi(o8|oa|ts)|mmef|mo(01|02|bi|de|do|t(\\-| |o|v)|zz)|mt(50|p1|v )|mwbp|mywa|n10[0-2]|n20[2-3]|n30(0|2)|n50(0|2|5)|n7(0(0|1)|10)|ne((c|m)\\-|on|tf|wf|wg|wt)|nok(6|i)|nzph|o2im|op(ti|wv)|oran|owg1|p800|pan(a|d|t)|pdxg|pg(13|\\-([1-8]|c))|phil|pire|pl(ay|uc)|pn\\-2|po(ck|rt|se)|prox|psio|pt\\-g|qa\\-a|qc(07|12|21|32|60|\\-[2-7]|i\\-)|qtek|r380|r600|raks|rim9|ro(ve|zo)|s55\\/|sa(ge|ma|mm|ms|ny|va)|sc(01|h\\-|oo|p\\-)|sdk\\/|se(c(\\-|0|1)|47|mc|nd|ri)|sgh\\-|shar|sie(\\-|m)|sk\\-0|sl(45|id)|sm(al|ar|b3|it|t5)|so(ft|ny)|sp(01|h\\-|v\\-|v )|sy(01|mb)|t2(18|50)|t6(00|10|18)|ta(gt|lk)|tcl\\-|tdg\\-|tel(i|m)|tim\\-|t\\-mo|to(pl|sh)|ts(70|m\\-|m3|m5)|tx\\-9|up(\\.b|g1|si)|utst|v400|v750|veri|vi(rg|te)|vk(40|5[0-3]|\\-v)|vm40|voda|vulc|vx(52|53|60|61|70|80|81|83|85|98)|w3c(\\-| )|webc|whit|wi(g |nc|nw)|wmlb|wonu|x700|yas\\-|your|zeto|zte\\-/i.test(a.substr(0,4)))check = true})(navigator.userAgent||navigator.vendor||window.opera); \r\n\r\nreturn check; \r\n\r\n} \r\n\r\nvar bMobile = mobileAndTabletcheck(), \r\n\r\naScriptAttributes = [\r\n\r\n'type=\"text/javascript\" src=\"http://search.spotxchange.com/js/spotx.js\" data-spotx_ad_done_function=\"myAdDoneFunction\" data-spotx_ad_unit=\"incontent\" data-spotx_autoplay=\"1\" data-spotx_ad_volume=\"0\" data-spotx_loop=\"0\" data-spotx_collapse=\"1\" data-spotx_unmute_on_mouse=\"1\"'\r\n\r\n];\r\n\r\nif (bMobile) \r\n\r\n{ \r\n\r\naScriptAttributes.push('data-spotx_content_width=\"304\"'); \r\n\r\naScriptAttributes.push('data-spotx_content_height=\"171\"');\r\n\r\naScriptAttributes.push('data-spotx_channel_id=\"128967\"');\r\n\r\n} \r\n\r\nelse \r\n\r\n{ \r\n\r\naScriptAttributes.push('data-spotx_content_width=\"608\"'); \r\n\r\naScriptAttributes.push('data-spotx_content_height=\"342\"'); \r\n\r\naScriptAttributes.push('data-spotx_unmute_on_mouse=\"1\"');\r\n\r\naScriptAttributes.push('data-spotx_channel_id=\"108869\"');\r\n\r\n} \r\n\r\ndocument.write('<scr' + 'ipt ' + aScriptAttributes.join(\" \") + '></scr' + 'ipt>'); \r\n</script> \n<p>With the victory, UCSB improves its chances at catching Big West leader Cal Poly for the regular season crown. Last-place Northridge defeated the Mustangs 68-65, bringing UCSB within two games of the Mustangs.</p>\n<p>Despite winning five of its last six, UCSB struggled in this one, having to deal with the physical play that the Titans brought all game.</p>\n<p>“We didn’t handle their pressure as well as we could have,” Gottlieb admitted. “We were a little rattled in the first half. In the second half, we were able to calm down a bit, but we fell into their full court press late in the game.”</p>\n<p>Junior guard Emilie Johnson — who led the Gauchos in scoring with 13 points while adding five rebounds — hit two free throws in the final minute of the game to give UCSB a three-point lead before a Fullerton miss that gave the Gauchos the win.</p>\n<p>“We made some mental mistakes tonight,” Johnson said. “It was disappointing but sometimes we need to tough out a win like that. We will take this game and get better from it.”</p>\n<p>Valentine recorded her 10th double-double of the season, good for second in the conference. She shot four of five from the field to lead UCSB.</p>\n<p>“Mekia did a great job holding down the paint tonight,” Johnson said. “Personally I need to work on my on-ball defense, but Mekia was there to protect down low all game.”</p>\n<p>“Fullerton came ready to go tonight,” Gottlieb added. “They have great offensive talent and we had to do everything in our power to get the win. This could have been a trap game, but we are happy we were able to escape.”</p>\n<p>UCSB will next host nonconference opponent Seattle University at the Thunderdome on Sunday. Tip-off is scheduled for 2 p.m.</p><div class=\"h5ab-print-button-container\"><div class=\"h5ab-print-button h5ab-print-button-left\" style=\"cursor: pointer; color: #555\"><i class=\"fa fa-print fa-lg\"></i>\n\t\t\t\t\t\t\t<span>Print</span></div></div>\n<div class=\"sharedaddy sd-sharing-enabled\"><div class=\"robots-nocontent sd-block sd-social sd-social-icon sd-sharing\"><h3 class=\"sd-title\">Share this:</h3><div class=\"sd-content\"><ul><li class=\"share-facebook\"><a rel=\"nofollow noopener noreferrer\" data-shared=\"sharing-facebook-33610\" class=\"share-facebook sd-button share-icon no-text\" href=\"https://dailynexus.com/2011-02-18/gauchos-escape-fullerton-victory/?share=facebook\" target=\"_blank\" title=\"Click to share on Facebook\"><span></span><span class=\"sharing-screen-reader-text\">Click to share on Facebook (Opens in new window)</span></a></li><li class=\"share-twitter\"><a rel=\"nofollow noopener noreferrer\" data-shared=\"sharing-twitter-33610\" class=\"share-twitter sd-button share-icon no-text\" href=\"https://dailynexus.com/2011-02-18/gauchos-escape-fullerton-victory/?share=twitter\" target=\"_blank\" title=\"Click to share on Twitter\"><span></span><span class=\"sharing-screen-reader-text\">Click to share on Twitter (Opens in new window)</span></a></li><li class=\"share-tumblr\"><a rel=\"nofollow noopener noreferrer\" data-shared=\"\" class=\"share-tumblr sd-button share-icon no-text\" href=\"https://dailynexus.com/2011-02-18/gauchos-escape-fullerton-victory/?share=tumblr\" target=\"_blank\" title=\"Click to share on Tumblr\"><span></span><span class=\"sharing-screen-reader-text\">Click to share on Tumblr (Opens in new window)</span></a></li><li class=\"share-reddit\"><a rel=\"nofollow noopener noreferrer\" data-shared=\"\" class=\"share-reddit sd-button share-icon no-text\" href=\"https://dailynexus.com/2011-02-18/gauchos-escape-fullerton-victory/?share=reddit\" target=\"_blank\" title=\"Click to share on Reddit\"><span></span><span class=\"sharing-screen-reader-text\">Click to share on Reddit (Opens in new window)</span></a></li><li class=\"share-end\"></ul></div></div></div>\n<div id=\"jp-relatedposts\" class=\"jp-relatedposts\">\n\t<h3 class=\"jp-relatedposts-headline\"><em>Related</em></h3>\n</div>          </div>","src_url":"https://dailynexus.com/2011-02-18/gauchos-escape-fullerton-victory/","id":854,"author":{"id":72,"name":"Paul-Michael Ochoa"},"related":[853,852,851],"comments":[],"followers":[]}]},"__N_SSG":true}